{
  "generated_at": null,
  "projects": {
    "root": {
      "venv": {
        "path": "C:\\Users\\Bryan\\OneDrive\\AI\\venv\\Scripts\\python.exe",
        "exists": true
      },
      "requirements": "C:\\Users\\Bryan\\OneDrive\\AI\\requirements.txt"
    },
    "quantum-ai": {
      "venv": {
        "path": "C:\\Users\\Bryan\\OneDrive\\AI\\quantum-ai\\venv\\Scripts\\python.exe",
        "exists": true
      },
      "requirements": "C:\\Users\\Bryan\\OneDrive\\AI\\quantum-ai\\requirements.txt"
    },
    "talk-to-ai": {
      "venv": {
        "path": "C:\\Users\\Bryan\\OneDrive\\AI\\talk-to-ai\\venv\\Scripts\\python.exe",
        "exists": true
      },
      "requirements": "C:\\Users\\Bryan\\OneDrive\\AI\\talk-to-ai\\requirements.txt"
    },
    "phi-lora": {
      "venv": {
        "path": "C:\\Users\\Bryan\\OneDrive\\AI\\AI\\microsoft_phi-silica-3.6_v1\\venv\\Scripts\\python.exe",
        "exists": true
      },
      "requirements": "C:\\Users\\Bryan\\OneDrive\\AI\\AI\\microsoft_phi-silica-3.6_v1\\requirements.txt"
    }
  },
  "orchestrators": {
    "autotrain": {
      "name": "autotrain",
      "status": "ok",
      "script": "C:\\Users\\Bryan\\OneDrive\\AI\\scripts\\autotrain.py",
      "return_code": 0,
      "jobs_parsed": [],
      "stdout_tail": "-3.6_v1\\\\scripts\\\\train_lora.py\",\n    \"--config\",\n    \"AI/microsoft_phi-silica-3.6_v1/lora/lora.yaml\",\n    \"--dataset\",\n    \"datasets/chat/dolly\",\n    \"--hf-model-id\",\n    \"microsoft/Phi-3.5-mini-instruct\",\n    \"--learning-rate\",\n    \"0.0002\",\n    \"--lora-dropout\",\n    \"0.1\",\n    \"--epochs\",\n    \"3\",\n    \"--save-dir\",\n    \"data_out/lora_training/phi35_max_performance\"\n  ],\n  \"start_time\": \"20251123T052119Z\",\n  \"status\": \"validated\",\n  \"return_code\": null,\n  \"log\": \"C:\\\\Users\\\\Bryan\\\\OneDrive\\\\AI\\\\data_out\\\\autotrain\\\\phi35_max_performance\\\\20251123T052119Z\\\\stdout.log\",\n  \"output_dir\": null\n}\n",
      "stderr_tail": ""
    },
    "quantum_autorun": {
      "name": "quantum_autorun",
      "status": "ok",
      "script": "C:\\Users\\Bryan\\OneDrive\\AI\\scripts\\quantum_autorun.py",
      "return_code": 0,
      "jobs_parsed": [],
      "stdout_tail": "quantum.py\",\n    \"--backend\",\n    \"ionq.simulator\",\n    \"--shots\",\n    \"100\"\n  ],\n  \"start_time\": \"20251123T052119Z\",\n  \"status\": \"validated\",\n  \"return_code\": null,\n  \"log\": \"C:\\\\Users\\\\Bryan\\\\OneDrive\\\\AI\\\\data_out\\\\quantum_autorun\\\\azure_ionq_simulator\\\\20251123T052119Z\\\\stdout.log\",\n  \"meta\": {\n    \"preset\": null,\n    \"csv\": null,\n    \"label_col\": null,\n    \"drop_cols\": null,\n    \"n_qubits\": null,\n    \"epochs\": null,\n    \"batch_size\": null,\n    \"learning_rate\": null,\n    \"test_size\": null,\n    \"azure_backend\": \"ionq.simulator\",\n    \"azure_shots\": 100,\n    \"azure_confirm_cost\": false\n  }\n}\n",
      "stderr_tail": ""
    }
  },
  "problems": []
}